<?xml version="1.0"?>
<CharacterClass xmlns:xsi="http://www.w3.org/2001/XMLSchema-instance" xmlns:xsd="http://www.w3.org/2001/XMLSchema">
  <BaseFile>Player</BaseFile>
  <SpineAnimation>suit_spy</SpineAnimation>
  <DisplayName>Intruder</DisplayName>
  <PlayerType>Spy</PlayerType>
  <ArtifactCost>2</ArtifactCost>

  <ArmMovementScaleX>0.5</ArmMovementScaleX>
  <ArmMovementScaleY>0.4</ArmMovementScaleY>

  <MaxHull>15</MaxHull>
  <StartHull>15</StartHull>

  <Description>
    This slim infiltration suit has found underground success with warring corporations for its clandestine abilities. Though not armoured for prolonged combat, it is equipped with advanced stealth gadgets and a short ranged teleporter, allowing canny pilots to slip through weak spots in defences.

-TRANSLOCATOR: Launchable short range teleport beacon.
-LOCKPICK: Can unlock locked doors without keys.</Description>

  <SkinAtlases>
    <SkinAtlas>
      <Name>Gentle Touch</Name>
      <Atlas>suit_spy</Atlas>
    </SkinAtlas>
    <SkinAtlas>
      <Name>Vengeance</Name>
      <Atlas>suit_spy_02</Atlas>
    </SkinAtlas>
    <SkinAtlas>
      <Name>Tallgeese</Name>
      <Atlas>suit_spy_03</Atlas>
    </SkinAtlas>
    <SkinAtlas>
      <Name>Mistletoe</Name>
      <Atlas>suit_spy_04</Atlas>
    </SkinAtlas>
  </SkinAtlases>
  
  <StartLoadOutAmounts>
    <int>3</int>
    <int>3</int>
    <int>1</int>
    <int>3</int>
  </StartLoadOutAmounts>

  <StartLoadOut>
    <string>Weapons\hushpuppy</string>
    <string>Weapons\shotgun_eject</string>
    <string>Weapons\shield_reflect</string>
    <string>Weapons\shotgun_doom</string>
  </StartLoadOut>

  <StartLoadOutAmounts>
    <int>3</int>
    <int>1</int>
    <int>1</int>
    <int>3</int>
  </StartLoadOutAmounts>

  <StartItemLoadOut>
    <string>Items\healthpack_micpack9</string>
    <string>Items\hazard_coat3</string>
    <string>Items\invisibility_potion</string>
    <string>Items\demo_bomb_huge</string>
  </StartItemLoadOut>
  
  <StartLoadOutBase>
    <string>Items\healthpack_small</string>
    <string>Items\sensorsuite</string>
    <string>Items\key</string>
  </StartLoadOutBase>

  <PassiveItems>
    <string>Items\laser_sight</string>
  </PassiveItems>
  
</CharacterClass>